dsfet/__init__.py
dsfet/fe_1mol.py
drug_smile_fet-1.0.5.dist-info/LICENSE
drug_smile_fet-1.0.5.dist-info/METADATA
drug_smile_fet-1.0.5.dist-info/WHEEL
drug_smile_fet-1.0.5.dist-info/top_level.txt
drug_smile_fet-1.0.5.dist-info/RECORD
