Metadata-Version: 2.1
Name: drug-smile-fet
Version: 1.0.5
Summary: This tool provides methods to extract meaningful features from drug SMILES for AI-Based Drug Development.
Home-page: https://github.com/rahulsharma-rs/drug-smile-fet
Author: Rahul Sharma
Author-email: rahul_rs.sharma@hotmail.com
License: MIT
Keywords: Drug SMILE,Feature Extraction,NLP,Morgan Fingerprints,Drug Discovery,Drug Development,AI-Based Drug Discovery,AI-Based Drug Development
Classifier: Programming Language :: Python :: 3
Classifier: License :: OSI Approved :: MIT License
Classifier: Operating System :: OS Independent
Requires-Python: >=3.8
License-File: LICENSE
Requires-Dist: scikit-learn
Requires-Dist: pandas
